oomnitza_ssrf_protection/__init__.py
oomnitza_ssrf_protection/ssrf_protection.py
oomnitza_ssrf_protection/oom_async/__init__.py
oomnitza_ssrf_protection/oom_async/ssrf_protection.py
oomnitza_ssrf_protection/oom_sync/__init__.py
oomnitza_ssrf_protection/oom_sync/ssrf_protection.py
oomnitza_ssrf_protection-0.1.5.dist-info/LICENSE
oomnitza_ssrf_protection-0.1.5.dist-info/METADATA
oomnitza_ssrf_protection-0.1.5.dist-info/WHEEL
oomnitza_ssrf_protection-0.1.5.dist-info/top_level.txt
oomnitza_ssrf_protection-0.1.5.dist-info/RECORD
