Metadata-Version: 2.1
Name: oomnitza-ssrf-protection
Version: 0.1.5
Summary: Contains reusable logic to apply Oomnitza ssrf protection.
Home-page: https://bitbucket.org/oomnitza/oomnitza-ssrf-protection
Author: Oomnitza, Andrei Liauchuk and others
Author-email: andrei.liauchuk@oomnitza.com
License: MIT
Keywords: oomnitza
Platform: unix
Platform: linux
Platform: osx
Classifier: Development Status :: 2 - Pre-Alpha
Classifier: Intended Audience :: Developers
Classifier: License :: OSI Approved :: MIT License
Classifier: Natural Language :: English
Classifier: Programming Language :: Python :: 3
Classifier: Programming Language :: Python :: 3 :: Only
Classifier: Programming Language :: Python :: 3.6
Classifier: Programming Language :: Python :: 3.7
Classifier: Programming Language :: Python :: 3.8
Classifier: Programming Language :: Python :: 3.9
Classifier: Programming Language :: Python :: 3.10
Classifier: Topic :: Software Development :: Libraries
Classifier: Topic :: Utilities
Requires-Python: >=3.6
License-File: LICENSE
Requires-Dist: aiodns ==3.0.0
Requires-Dist: pycares ==4.2.2
Provides-Extra: tests
Requires-Dist: pytest >=3 ; extra == 'tests'
Requires-Dist: pytest-lazy-fixture >=0.6.3 ; extra == 'tests'
Requires-Dist: pytest-cov >=2 ; extra == 'tests'
Requires-Dist: pytest-aiohttp >=0.3.0 ; extra == 'tests'
